kld7/__init__.py
kld7/constants.py
kld7/device.py
kld7-0.2.1.dist-info/METADATA
kld7-0.2.1.dist-info/WHEEL
kld7-0.2.1.dist-info/top_level.txt
kld7-0.2.1.dist-info/RECORD
