Metadata-Version: 2.1
Name: kld7
Version: 0.2.1
Summary: K-LD7 Doppler radar sensor driver
Home-page: https://github.com/nickovs/kld7
Author: Nicko van Someren
Author-email: nicko@nicko.org
Keywords: radar,Doppler
Classifier: Development Status :: 4 - Beta
Classifier: Programming Language :: Python :: 3
Classifier: License :: OSI Approved :: Apache Software License
Classifier: Operating System :: OS Independent
Requires-Python: >=3.6
Requires-Dist: pyserial
